[
  {
    "title": "EŞİTSİZLİKLER 1. BÖLÜM 1. DERS",
    "stream_url": "https://karinca-video.mncdn.com/smil:48d27520-6e6c-4023-b0c4-0fc5751ed5b3_smil.smil/playlist.m3u8",
    "instructor_name": "Recep Üstünel",
    "duration": "19:08"
  },
  {
    "title": "EŞİTSİZLİKLER 1. BÖLÜM 2. DERS",
    "stream_url": "https://karinca-video.mncdn.com/smil:e517c72b-4264-4619-ae63-d20d87c5fd4d_smil.smil/playlist.m3u8",
    "instructor_name": "Recep Üstünel",
    "duration": "24:25"
  },
  {
    "title": "EŞİTSİZLİKLER 1. BÖLÜM 3. DERS",
    "stream_url": "https://karinca-video.mncdn.com/smil:8865d736-8d53-46d0-b1a6-bc846d90336c_smil.smil/playlist.m3u8",
    "instructor_name": "Recep Üstünel",
    "duration": "12:04"
  },
  {
    "title": "EŞİTSİZLİKLER 1. BÖLÜM 4. DERS",
    "stream_url": "https://karinca-video.mncdn.com/smil:b9abe8f3-48d7-4093-816b-3621c9276306_smil.smil/playlist.m3u8",
    "instructor_name": "Recep Üstünel",
    "duration": "27:02"
  },
  {
    "title": "EŞİTSİZLİKLER 2. BÖLÜM 1. DERS",
    "stream_url": "https://karinca-video.mncdn.com/smil:38c16a82-d38e-477c-b856-87b86e75e858_smil.smil/playlist.m3u8",
    "instructor_name": "Recep Üstünel",
    "duration": "17:32"
  },
  {
    "title": "EŞİTSİZLİKLER 2. BÖLÜM 2. DERS",
    "stream_url": "https://karinca-video.mncdn.com/smil:ac7831d7-9205-4ed5-a2e1-558f03829e44_smil.smil/playlist.m3u8",
    "instructor_name": "Recep Üstünel",
    "duration": "12:24"
  },
  {
    "title": "FONKSİYONLAR 1. DERS",
    "stream_url": "https://karinca-video.mncdn.com/smil:440ccca0-1cb3-43b8-9b9a-b2639ea5e3fa_smil.smil/playlist.m3u8",
    "instructor_name": "Recep Üstünel",
    "duration": "08:40"
  },
  {
    "title": "FONKSİYONLAR 10. DERS",
    "stream_url": "https://karinca-video.mncdn.com/smil:943a07f1-37e9-42b7-b2c2-feffc14219f6_smil.smil/playlist.m3u8",
    "instructor_name": "Recep Üstünel",
    "duration": "20:56"
  },
  {
    "title": "FONKSİYONLAR 11. DERS",
    "stream_url": "https://karinca-video.mncdn.com/smil:686b0807-6f53-4064-8481-97cd5b9ad686_smil.smil/playlist.m3u8",
    "instructor_name": "Recep Üstünel",
    "duration": "13:52"
  },
  {
    "title": "FONKSİYONLAR 12. DERS",
    "stream_url": "https://karinca-video.mncdn.com/smil:ec3f6521-2139-42b9-a3bc-8b165afc3f8e_smil.smil/playlist.m3u8",
    "instructor_name": "Recep Üstünel",
    "duration": "19:22"
  },
  {
    "title": "FONKSİYONLAR 13. DERS",
    "stream_url": "https://karinca-video.mncdn.com/smil:fd596cd4-2101-49c6-b2ec-6d9288ad55a4_smil.smil/playlist.m3u8",
    "instructor_name": "Recep Üstünel",
    "duration": "14:38"
  },
  {
    "title": "FONKSİYONLAR 14. DERS",
    "stream_url": "https://karinca-video.mncdn.com/smil:6414a956-3d56-4673-af1e-a4c76bdc1c3e_smil.smil/playlist.m3u8",
    "instructor_name": "Recep Üstünel",
    "duration": "16:51"
  },
  {
    "title": "FONKSİYONLAR 15. DERS",
    "stream_url": "https://karinca-video.mncdn.com/smil:da44b7b1-6730-4447-8cae-b57726a1f569_smil.smil/playlist.m3u8",
    "instructor_name": "Recep Üstünel",
    "duration": "12:38"
  },
  {
    "title": "FONKSİYONLAR 16. DERS",
    "stream_url": "https://karinca-video.mncdn.com/smil:3141a2db-f669-4ff1-b1e0-cbb66e1f7ff0_smil.smil/playlist.m3u8",
    "instructor_name": "Recep Üstünel",
    "duration": "10:32"
  },
  {
    "title": "FONKSİYONLAR 17. DERS",
    "stream_url": "https://karinca-video.mncdn.com/smil:1aca070a-895c-42a4-985c-dc6c03629732_smil.smil/playlist.m3u8",
    "instructor_name": "Recep Üstünel",
    "duration": "12:56"
  },
  {
    "title": "FONKSİYONLAR 18. DERS",
    "stream_url": "https://karinca-video.mncdn.com/smil:a5bee05b-5d03-4582-ab9b-2e2ea42a0cd4_smil.smil/playlist.m3u8",
    "instructor_name": "Recep Üstünel",
    "duration": "09:04"
  },
  {
    "title": "FONKSİYONLAR 19. DERS",
    "stream_url": "https://karinca-video.mncdn.com/smil:562fb8de-c3fc-44bc-802b-9d84f955c142_smil.smil/playlist.m3u8",
    "instructor_name": "Recep Üstünel",
    "duration": "13:12"
  },
  {
    "title": "FONKSİYONLAR 2. DERS",
    "stream_url": "https://karinca-video.mncdn.com/smil:43972642-cf22-4fca-a07f-5c83b9af429d_smil.smil/playlist.m3u8",
    "instructor_name": "Recep Üstünel",
    "duration": "09:07"
  },
  {
    "title": "FONKSİYONLAR 20. DERS",
    "stream_url": "https://karinca-video.mncdn.com/smil:363bc57b-db38-43c1-a36c-54a00789872c_smil.smil/playlist.m3u8",
    "instructor_name": "Recep Üstünel",
    "duration": "17:13"
  },
  {
    "title": "FONKSİYONLAR 3. DERS",
    "stream_url": "https://karinca-video.mncdn.com/smil:3ae0105f-4648-42aa-8cf5-ea9400fbdd32_smil.smil/playlist.m3u8",
    "instructor_name": "Recep Üstünel",
    "duration": "08:09"
  },
  {
    "title": "FONKSİYONLAR 4. DERS",
    "stream_url": "https://karinca-video.mncdn.com/smil:8ed6384b-5b74-4096-acb5-ada6b5a3d425_smil.smil/playlist.m3u8",
    "instructor_name": "Recep Üstünel",
    "duration": "12:17"
  },
  {
    "title": "FONKSİYONLAR 5. DERS",
    "stream_url": "https://karinca-video.mncdn.com/smil:495e78e5-6eb9-4a23-88bf-92918d6e1130_smil.smil/playlist.m3u8",
    "instructor_name": "Recep Üstünel",
    "duration": "07:35"
  },
  {
    "title": "FONKSİYONLAR 6. DERS",
    "stream_url": "https://karinca-video.mncdn.com/smil:ae65e865-d6a2-4501-91b0-e769e7dc2658_smil.smil/playlist.m3u8",
    "instructor_name": "Recep Üstünel",
    "duration": "12:50"
  },
  {
    "title": "FONKSİYONLAR 7. DERS",
    "stream_url": "https://karinca-video.mncdn.com/smil:1e1d1c27-1fbe-4dfc-98f7-cf8e62faaf32_smil.smil/playlist.m3u8",
    "instructor_name": "Recep Üstünel",
    "duration": "10:41"
  },
  {
    "title": "FONKSİYONLAR 8. DERS",
    "stream_url": "https://karinca-video.mncdn.com/smil:f9b371f7-342f-436f-bfb6-9d197ddd76b2_smil.smil/playlist.m3u8",
    "instructor_name": "Recep Üstünel",
    "duration": "15:31"
  },
  {
    "title": "FONKSİYONLAR 9. DERS",
    "stream_url": "https://karinca-video.mncdn.com/smil:8f3dd0f9-1629-45a0-af7d-809a56fffccc_smil.smil/playlist.m3u8",
    "instructor_name": "Recep Üstünel",
    "duration": "09:42"
  },
  {
    "title": "II. DERECEDEN DENKLEMLER 1. DERS",
    "stream_url": "https://karinca-video.mncdn.com/smil:5e90e4de-3697-4ea9-808d-7f934b50026a_smil.smil/playlist.m3u8",
    "instructor_name": "Recep Üstünel",
    "duration": "16:19"
  },
  {
    "title": "II. DERECEDEN DENKLEMLER 2. DERS",
    "stream_url": "https://karinca-video.mncdn.com/smil:d7708603-6f6f-4aa1-811b-3b055612b96f_smil.smil/playlist.m3u8",
    "instructor_name": "Recep Üstünel",
    "duration": "08:22"
  },
  {
    "title": "II. DERECEDEN DENKLEMLER 3. DERS",
    "stream_url": "https://karinca-video.mncdn.com/smil:18ebf7a4-24a4-4df0-9ad8-2481f0635e0a_smil.smil/playlist.m3u8",
    "instructor_name": "Recep Üstünel",
    "duration": "15:32"
  },
  {
    "title": "II. DERECEDEN DENKLEMLER 4. DERS",
    "stream_url": "https://karinca-video.mncdn.com/smil:44e33b11-f43f-48f2-af73-5806f3938220_smil.smil/playlist.m3u8",
    "instructor_name": "Recep Üstünel",
    "duration": "16:15"
  },
  {
    "title": "II. DERECEDEN DENKLEMLER 5. DERS",
    "stream_url": "https://karinca-video.mncdn.com/smil:f3eb8b9c-4923-4e21-a528-42f38837d2ac_smil.smil/playlist.m3u8",
    "instructor_name": "Recep Üstünel",
    "duration": "11:21"
  },
  {
    "title": "II. DERECEDEN DENKLEMLER 6. DERS",
    "stream_url": "https://karinca-video.mncdn.com/smil:5eea1bec-9db1-477d-9869-f44e7ee9dd28_smil.smil/playlist.m3u8",
    "instructor_name": "Recep Üstünel",
    "duration": "11:14"
  },
  {
    "title": "II. DERECEDEN DENKLEMLER 7. DERS",
    "stream_url": "https://karinca-video.mncdn.com/smil:1edece61-a6ed-4d88-b829-a52000d9462a_smil.smil/playlist.m3u8",
    "instructor_name": "Recep Üstünel",
    "duration": "09:59"
  },
  {
    "title": "II. DERECEDEN DENKLEMLER 8. DERS",
    "stream_url": "https://karinca-video.mncdn.com/smil:6cbae5ed-b310-4c24-84ff-948d769757ea_smil.smil/playlist.m3u8",
    "instructor_name": "Recep Üstünel",
    "duration": "14:27"
  },
  {
    "title": "II. DERECEDEN DENKLEMLER 9. DERS",
    "stream_url": "https://karinca-video.mncdn.com/smil:1ba5b31c-3e51-44d4-8eaf-57e8308405b8_smil.smil/playlist.m3u8",
    "instructor_name": "Recep Üstünel",
    "duration": "19:05"
  },
  {
    "title": "POLİNOMLAR 1. BÖLÜM",
    "stream_url": "https://karinca-video.mncdn.com/smil:61132cb3-f575-4a4e-b8a0-b4b10271d0f6_smil.smil/playlist.m3u8",
    "instructor_name": "Recep Üstünel",
    "duration": "09:52"
  },
  {
    "title": "POLİNOMLAR 10. BÖLÜM 1. DERS",
    "stream_url": "https://karinca-video.mncdn.com/smil:b348fab0-3682-4861-8497-34c1556fc6e1_smil.smil/playlist.m3u8",
    "instructor_name": "Recep Üstünel",
    "duration": "06:01"
  },
  {
    "title": "POLİNOMLAR 10. BÖLÜM 2. DERS",
    "stream_url": "https://karinca-video.mncdn.com/smil:2391aa26-5c87-4ad4-9e48-5257dce09148_smil.smil/playlist.m3u8",
    "instructor_name": "Recep Üstünel",
    "duration": "10:40"
  },
  {
    "title": "POLİNOMLAR 11. BÖLÜM 1. DERS",
    "stream_url": "https://karinca-video.mncdn.com/smil:1c7c6e14-3c45-4b69-97b3-cacdd102b97b_smil.smil/playlist.m3u8",
    "instructor_name": "Recep Üstünel",
    "duration": "08:06"
  },
  {
    "title": "POLİNOMLAR 11. BÖLÜM 2. DERS",
    "stream_url": "https://karinca-video.mncdn.com/smil:6e459aae-9744-4a5d-a287-d52e38801cd8_smil.smil/playlist.m3u8",
    "instructor_name": "Recep Üstünel",
    "duration": "07:42"
  },
  {
    "title": "POLİNOMLAR 11. BÖLÜM 3. DERS",
    "stream_url": "https://karinca-video.mncdn.com/smil:d8870868-6fee-42c9-8b1e-d3ee23c415c6_smil.smil/playlist.m3u8",
    "instructor_name": "Recep Üstünel",
    "duration": "09:23"
  },
  {
    "title": "POLİNOMLAR 2. BÖLÜM ",
    "stream_url": "https://karinca-video.mncdn.com/smil:305715cf-7ca9-4fe5-8b00-1135bffb3ee9_smil.smil/playlist.m3u8",
    "instructor_name": "Recep Üstünel",
    "duration": "06:47"
  },
  {
    "title": "POLİNOMLAR 3. BÖLÜM 1. DERS",
    "stream_url": "https://karinca-video.mncdn.com/smil:2922f553-23dd-4a80-86b2-a99c682fe28e_smil.smil/playlist.m3u8",
    "instructor_name": "Recep Üstünel",
    "duration": "11:42"
  },
  {
    "title": "POLİNOMLAR 3. BÖLÜM 2. DERS",
    "stream_url": "https://karinca-video.mncdn.com/smil:160100e4-31f3-4630-8ffc-6f9600ef4184_smil.smil/playlist.m3u8",
    "instructor_name": "Recep Üstünel",
    "duration": "10:00"
  },
  {
    "title": "POLİNOMLAR 4. BÖLÜM 1. DERS",
    "stream_url": "https://karinca-video.mncdn.com/smil:6a7fdfaa-55fe-4fb2-8533-b0572686df16_smil.smil/playlist.m3u8",
    "instructor_name": "Recep Üstünel",
    "duration": "09:03"
  },
  {
    "title": "POLİNOMLAR 4. BÖLÜM 2. DERS",
    "stream_url": "https://karinca-video.mncdn.com/smil:22819181-d96e-4343-98b8-68b8a0600bb5_smil.smil/playlist.m3u8",
    "instructor_name": "Recep Üstünel",
    "duration": "15:05"
  },
  {
    "title": "POLİNOMLAR 5. BÖLÜM",
    "stream_url": "https://karinca-video.mncdn.com/smil:b1b16cc1-7675-4ed6-a45b-31d5ca98ab96_smil.smil/playlist.m3u8",
    "instructor_name": "Recep Üstünel",
    "duration": "12:45"
  },
  {
    "title": "POLİNOMLAR 6. BÖLÜM",
    "stream_url": "https://karinca-video.mncdn.com/smil:c299cfb2-3c7c-44d7-851b-090c94f19d4c_smil.smil/playlist.m3u8",
    "instructor_name": "Recep Üstünel",
    "duration": "08:30"
  },
  {
    "title": "POLİNOMLAR 7. BÖLÜM 1. DERS",
    "stream_url": "https://karinca-video.mncdn.com/smil:089096cb-ae15-414d-bc02-2e7a4bfab600_smil.smil/playlist.m3u8",
    "instructor_name": "Recep Üstünel",
    "duration": "09:27"
  },
  {
    "title": "POLİNOMLAR 7. BÖLÜM 2. DERS",
    "stream_url": "https://karinca-video.mncdn.com/smil:a5cdf424-266f-44a4-aa36-c76d59ad6d0c_smil.smil/playlist.m3u8",
    "instructor_name": "Recep Üstünel",
    "duration": "08:02"
  },
  {
    "title": "POLİNOMLAR 7. BÖLÜM 3. DERS",
    "stream_url": "https://karinca-video.mncdn.com/smil:573eaa52-4b8f-4a48-8cf5-208eb4edda50_smil.smil/playlist.m3u8",
    "instructor_name": "Recep Üstünel",
    "duration": "09:06"
  },
  {
    "title": "POLİNOMLAR 8. BÖLÜM 1. DERS",
    "stream_url": "https://karinca-video.mncdn.com/smil:9e79646e-00f4-48a8-9a7d-7fbfb44ac08c_smil.smil/playlist.m3u8",
    "instructor_name": "Recep Üstünel",
    "duration": "10:47"
  },
  {
    "title": "POLİNOMLAR 9. BÖLÜM 1. DERS",
    "stream_url": "https://karinca-video.mncdn.com/smil:ad9160f8-3fad-4149-9a67-6bdeaca5cf92_smil.smil/playlist.m3u8",
    "instructor_name": "Recep Üstünel",
    "duration": "07:23"
  }
]
